odoo10_addon_l10n_fr_chorus_account-10.0.3.0.0.99.dev10-py3.8-nspkg.pth
odoo/addons/l10n_fr_chorus_account/README.rst
odoo/addons/l10n_fr_chorus_account/__init__.py
odoo/addons/l10n_fr_chorus_account/__manifest__.py
odoo/addons/l10n_fr_chorus_account/data/cron.xml
odoo/addons/l10n_fr_chorus_account/data/mail_template.xml
odoo/addons/l10n_fr_chorus_account/data/transmit_method.xml
odoo/addons/l10n_fr_chorus_account/demo/demo.xml
odoo/addons/l10n_fr_chorus_account/i18n/am.po
odoo/addons/l10n_fr_chorus_account/i18n/bg.po
odoo/addons/l10n_fr_chorus_account/i18n/ca.po
odoo/addons/l10n_fr_chorus_account/i18n/da.po
odoo/addons/l10n_fr_chorus_account/i18n/de.po
odoo/addons/l10n_fr_chorus_account/i18n/el_GR.po
odoo/addons/l10n_fr_chorus_account/i18n/es.po
odoo/addons/l10n_fr_chorus_account/i18n/es_ES.po
odoo/addons/l10n_fr_chorus_account/i18n/es_MX.po
odoo/addons/l10n_fr_chorus_account/i18n/fi.po
odoo/addons/l10n_fr_chorus_account/i18n/fr.po
odoo/addons/l10n_fr_chorus_account/i18n/fr_CH.po
odoo/addons/l10n_fr_chorus_account/i18n/gl.po
odoo/addons/l10n_fr_chorus_account/i18n/hr.po
odoo/addons/l10n_fr_chorus_account/i18n/it.po
odoo/addons/l10n_fr_chorus_account/i18n/l10n_fr_chorus_account.pot
odoo/addons/l10n_fr_chorus_account/i18n/nb_NO.po
odoo/addons/l10n_fr_chorus_account/i18n/nl.po
odoo/addons/l10n_fr_chorus_account/i18n/pt.po
odoo/addons/l10n_fr_chorus_account/i18n/pt_BR.po
odoo/addons/l10n_fr_chorus_account/i18n/pt_PT.po
odoo/addons/l10n_fr_chorus_account/i18n/sl.po
odoo/addons/l10n_fr_chorus_account/i18n/tr.po
odoo/addons/l10n_fr_chorus_account/migrations/10.0.2.1.0/post-migration.py
odoo/addons/l10n_fr_chorus_account/models/__init__.py
odoo/addons/l10n_fr_chorus_account/models/account_config_settings.py
odoo/addons/l10n_fr_chorus_account/models/account_invoice.py
odoo/addons/l10n_fr_chorus_account/models/chorus_flow.py
odoo/addons/l10n_fr_chorus_account/models/chorus_partner_service.py
odoo/addons/l10n_fr_chorus_account/models/company.py
odoo10_addon_l10n_fr_chorus_account-10.0.3.0.0.99.dev10.dist-info/METADATA
odoo10_addon_l10n_fr_chorus_account-10.0.3.0.0.99.dev10.dist-info/WHEEL
odoo10_addon_l10n_fr_chorus_account-10.0.3.0.0.99.dev10.dist-info/namespace_packages.txt
odoo10_addon_l10n_fr_chorus_account-10.0.3.0.0.99.dev10.dist-info/top_level.txt
odoo10_addon_l10n_fr_chorus_account-10.0.3.0.0.99.dev10.dist-info/RECORD
